truncate_and_write_to_sql/__init__.py
truncate_and_write_to_sql/methods.py
truncate_and_write_to_sql-0.1.1.dist-info/LICENSE
truncate_and_write_to_sql-0.1.1.dist-info/METADATA
truncate_and_write_to_sql-0.1.1.dist-info/WHEEL
truncate_and_write_to_sql-0.1.1.dist-info/top_level.txt
truncate_and_write_to_sql-0.1.1.dist-info/RECORD
