Metadata-Version: 2.1
Name: truncate-and-write-to-sql
Version: 0.1.1
Summary: Truncate existing table and write to the table with new entries
Home-page: https://github.com/MPettersen/truncate_and_write_to_sql
Author: Markus Pettersen
Author-email: mp.markus94@gmail.com
License: UNKNOWN
Platform: UNKNOWN
Classifier: Programming Language :: Python :: 3
Classifier: License :: OSI Approved :: MIT License
Classifier: Operating System :: OS Independent
Requires-Python: >=3.8
